{"stats":{"minecraft:custom":{"minecraft:jump":25,"minecraft:time_since_rest":1493,"minecraft:sprint_one_cm":7036,"minecraft:play_time":1493,"minecraft:walk_on_water_one_cm":523,"minecraft:time_since_death":1493,"minecraft:walk_one_cm":3157,"minecraft:total_world_time":1493,"minecraft:walk_under_water_one_cm":240,"minecraft:fall_one_cm":629,"minecraft:fly_one_cm":8005},"minecraft:mined":{"minecraft:short_grass":4,"minecraft:ice":1,"minecraft:spruce_leaves":1},"minecraft:picked_up":{"minecraft:wheat_seeds":1}},"DataVersion":3953}